Metadata-Version: 2.1
Name: quotesx
Version: 0.0.1
Summary: A package to get quotes
Home-page: UNKNOWN
Author: Mohammed Daniyal
Author-email: danides450@gmail.com
License: UNKNOWN
Keywords: quote,simple,effiecient,easy
Platform: UNKNOWN
Classifier: Intended Audience :: Developers
Classifier: Programming Language :: Python :: 3
Classifier: Operating System :: Unix
Classifier: Operating System :: MacOS :: MacOS X
Classifier: Operating System :: Microsoft :: Windows
License-File: LICENSE
